{"frames":{"log-full.png":{"frame":{"x":3,"y":3,"w":72,"h":800},"rotated":false,"trimed":false,"spriteSourceSize":{"x":0,"y":0,"w":72,"h":800},"sourceSize":{"w":72,"h":800}},"i-beam-body.png":{"frame":{"x":3,"y":806,"w":800,"h":64},"rotated":false,"trimed":false,"spriteSourceSize":{"x":0,"y":0,"w":800,"h":64},"sourceSize":{"w":800,"h":64}},"NPC-176.png":{"frame":{"x":78,"y":3,"w":321,"h":424},"rotated":false,"trimed":false,"spriteSourceSize":{"x":0,"y":0,"w":321,"h":424},"sourceSize":{"w":321,"h":424}},"log-half-2.png":{"frame":{"x":402,"y":3,"w":72,"h":424},"rotated":false,"trimed":false,"spriteSourceSize":{"x":0,"y":0,"w":72,"h":424},"sourceSize":{"w":72,"h":424}},"harpoon.png":{"frame":{"x":3,"y":873,"w":420,"h":58},"rotated":false,"trimed":false,"spriteSourceSize":{"x":0,"y":0,"w":420,"h":58},"sourceSize":{"w":420,"h":58}},"log-half-1.png":{"frame":{"x":477,"y":3,"w":73,"h":416},"rotated":false,"trimed":false,"spriteSourceSize":{"x":0,"y":0,"w":73,"h":416},"sourceSize":{"w":73,"h":416}},"meteor.png":{"frame":{"x":553,"y":3,"w":407,"h":401},"rotated":false,"trimed":false,"spriteSourceSize":{"x":0,"y":0,"w":407,"h":401},"sourceSize":{"w":407,"h":401}},"NPC-175.png":{"frame":{"x":402,"y":430,"w":304,"h":368},"rotated":false,"trimed":false,"spriteSourceSize":{"x":0,"y":0,"w":304,"h":368},"sourceSize":{"w":304,"h":368}},"harpoon-blood-3.png":{"frame":{"x":3,"y":934,"w":327,"h":46},"rotated":false,"trimed":false,"spriteSourceSize":{"x":0,"y":0,"w":327,"h":46},"sourceSize":{"w":327,"h":46}},"harpoon-blood-2.png":{"frame":{"x":78,"y":430,"w":311,"h":58},"rotated":false,"trimed":false,"spriteSourceSize":{"x":0,"y":0,"w":311,"h":58},"sourceSize":{"w":311,"h":58}},"harpoon-blood-5.png":{"frame":{"x":333,"y":934,"w":297,"h":58},"rotated":false,"trimed":false,"spriteSourceSize":{"x":0,"y":0,"w":297,"h":58},"sourceSize":{"w":297,"h":58}},"NPC-3.png":{"frame":{"x":78,"y":491,"w":118,"h":259},"rotated":false,"trimed":false,"spriteSourceSize":{"x":0,"y":0,"w":118,"h":259},"sourceSize":{"w":118,"h":259}},"harpoon-blood-1.png":{"frame":{"x":426,"y":873,"w":242,"h":54},"rotated":false,"trimed":false,"spriteSourceSize":{"x":0,"y":0,"w":242,"h":54},"sourceSize":{"w":242,"h":54}},"harpoon-blood-4.png":{"frame":{"x":3,"y":983,"w":226,"h":30},"rotated":false,"trimed":false,"spriteSourceSize":{"x":0,"y":0,"w":226,"h":30},"sourceSize":{"w":226,"h":30}},"NPC-185.png":{"frame":{"x":709,"y":407,"w":220,"h":170},"rotated":false,"trimed":false,"spriteSourceSize":{"x":0,"y":0,"w":220,"h":170},"sourceSize":{"w":220,"h":170}},"NPC-184.png":{"frame":{"x":709,"y":580,"w":220,"h":159},"rotated":false,"trimed":false,"spriteSourceSize":{"x":0,"y":0,"w":220,"h":159},"sourceSize":{"w":220,"h":159}},"harpoon-gun-body.png":{"frame":{"x":806,"y":742,"w":74,"h":216},"rotated":false,"trimed":false,"spriteSourceSize":{"x":0,"y":0,"w":74,"h":216},"sourceSize":{"w":74,"h":216}},"NPC-124.png":{"frame":{"x":883,"y":742,"w":93,"h":214},"rotated":false,"trimed":false,"spriteSourceSize":{"x":0,"y":0,"w":93,"h":214},"sourceSize":{"w":93,"h":214}},"NPC-91.png":{"frame":{"x":199,"y":491,"w":84,"h":209},"rotated":false,"trimed":false,"spriteSourceSize":{"x":0,"y":0,"w":84,"h":209},"sourceSize":{"w":84,"h":209}},"NPC-120.png":{"frame":{"x":286,"y":491,"w":86,"h":208},"rotated":false,"trimed":false,"spriteSourceSize":{"x":0,"y":0,"w":86,"h":208},"sourceSize":{"w":86,"h":208}},"NPC-319.png":{"frame":{"x":932,"y":407,"w":107,"h":202},"rotated":false,"trimed":false,"spriteSourceSize":{"x":0,"y":0,"w":107,"h":202},"sourceSize":{"w":107,"h":202}},"NPC-321.png":{"frame":{"x":963,"y":3,"w":107,"h":201},"rotated":false,"trimed":false,"spriteSourceSize":{"x":0,"y":0,"w":107,"h":201},"sourceSize":{"w":107,"h":201}},"harpoon-gun-base-2.png":{"frame":{"x":963,"y":207,"w":200,"h":197},"rotated":false,"trimed":false,"spriteSourceSize":{"x":0,"y":0,"w":200,"h":197},"sourceSize":{"w":200,"h":197}},"NPC-126.png":{"frame":{"x":1073,"y":3,"w":104,"h":193},"rotated":false,"trimed":false,"spriteSourceSize":{"x":0,"y":0,"w":104,"h":193},"sourceSize":{"w":104,"h":193}},"NPC-128.png":{"frame":{"x":979,"y":612,"w":104,"h":190},"rotated":false,"trimed":false,"spriteSourceSize":{"x":0,"y":0,"w":104,"h":190},"sourceSize":{"w":104,"h":190}},"NPC-125.png":{"frame":{"x":1042,"y":407,"w":93,"h":190},"rotated":false,"trimed":false,"spriteSourceSize":{"x":0,"y":0,"w":93,"h":190},"sourceSize":{"w":93,"h":190}},"NPC-318.png":{"frame":{"x":979,"y":805,"w":93,"h":190},"rotated":false,"trimed":false,"spriteSourceSize":{"x":0,"y":0,"w":93,"h":190},"sourceSize":{"w":93,"h":190}},"NPC-320.png":{"frame":{"x":1075,"y":805,"w":93,"h":189},"rotated":false,"trimed":false,"spriteSourceSize":{"x":0,"y":0,"w":93,"h":189},"sourceSize":{"w":93,"h":189}},"NPC-296.png":{"frame":{"x":1086,"y":600,"w":84,"h":188},"rotated":false,"trimed":false,"spriteSourceSize":{"x":0,"y":0,"w":84,"h":188},"sourceSize":{"w":84,"h":188}},"NPC-298.png":{"frame":{"x":1138,"y":407,"w":88,"h":188},"rotated":false,"trimed":false,"spriteSourceSize":{"x":0,"y":0,"w":88,"h":188},"sourceSize":{"w":88,"h":188}},"NPC-127.png":{"frame":{"x":1166,"y":199,"w":93,"h":187},"rotated":false,"trimed":false,"spriteSourceSize":{"x":0,"y":0,"w":93,"h":187},"sourceSize":{"w":93,"h":187}},"NPC-299.png":{"frame":{"x":1180,"y":3,"w":85,"h":187},"rotated":false,"trimed":false,"spriteSourceSize":{"x":0,"y":0,"w":85,"h":187},"sourceSize":{"w":85,"h":187}},"NPC-308.png":{"frame":{"x":1171,"y":791,"w":89,"h":186},"rotated":false,"trimed":false,"spriteSourceSize":{"x":0,"y":0,"w":89,"h":186},"sourceSize":{"w":89,"h":186}},"jet-flame.png":{"frame":{"x":1173,"y":598,"w":36,"h":183},"rotated":false,"trimed":false,"spriteSourceSize":{"x":0,"y":0,"w":36,"h":183},"sourceSize":{"w":36,"h":183}},"NPC-172.png":{"frame":{"x":1212,"y":598,"w":132,"h":181},"rotated":false,"trimed":false,"spriteSourceSize":{"x":0,"y":0,"w":132,"h":181},"sourceSize":{"w":132,"h":181}},"mouse-click-asset-13.png":{"frame":{"x":1229,"y":389,"w":160,"h":160},"rotated":false,"trimed":false,"spriteSourceSize":{"x":0,"y":0,"w":160,"h":160},"sourceSize":{"w":160,"h":160}},"mouse-click-asset-15.png":{"frame":{"x":1262,"y":193,"w":160,"h":160},"rotated":false,"trimed":false,"spriteSourceSize":{"x":0,"y":0,"w":160,"h":160},"sourceSize":{"w":160,"h":160}},"mouse-click-asset-12.png":{"frame":{"x":1268,"y":3,"w":158,"h":158},"rotated":false,"trimed":false,"spriteSourceSize":{"x":0,"y":0,"w":158,"h":158},"sourceSize":{"w":158,"h":158}},"mouse-click-asset-14.png":{"frame":{"x":1263,"y":782,"w":156,"h":156},"rotated":false,"trimed":false,"spriteSourceSize":{"x":0,"y":0,"w":156,"h":156},"sourceSize":{"w":156,"h":156}},"mouse-click-asset-10.png":{"frame":{"x":1347,"y":552,"w":154,"h":154},"rotated":false,"trimed":false,"spriteSourceSize":{"x":0,"y":0,"w":154,"h":154},"sourceSize":{"w":154,"h":154}},"mouse-click-asset-11.png":{"frame":{"x":1392,"y":356,"w":150,"h":150},"rotated":false,"trimed":false,"spriteSourceSize":{"x":0,"y":0,"w":150,"h":150},"sourceSize":{"w":150,"h":150}},"NPC-170.png":{"frame":{"x":1425,"y":164,"w":57,"h":145},"rotated":false,"trimed":false,"spriteSourceSize":{"x":0,"y":0,"w":57,"h":145},"sourceSize":{"w":57,"h":145}},"mouse-click-asset-8.png":{"frame":{"x":1429,"y":3,"w":145,"h":145},"rotated":false,"trimed":false,"spriteSourceSize":{"x":0,"y":0,"w":145,"h":145},"sourceSize":{"w":145,"h":145}},"NPC-171.png":{"frame":{"x":1485,"y":151,"w":51,"h":141},"rotated":false,"trimed":false,"spriteSourceSize":{"x":0,"y":0,"w":51,"h":141},"sourceSize":{"w":51,"h":141}},"mouse-click-asset-9.png":{"frame":{"x":1539,"y":151,"w":140,"h":140},"rotated":false,"trimed":false,"spriteSourceSize":{"x":0,"y":0,"w":140,"h":140},"sourceSize":{"w":140,"h":140}},"NPC-166.png":{"frame":{"x":1577,"y":3,"w":48,"h":137},"rotated":false,"trimed":false,"spriteSourceSize":{"x":0,"y":0,"w":48,"h":137},"sourceSize":{"w":48,"h":137}},"NPC-180.png":{"frame":{"x":199,"y":703,"w":136,"h":95},"rotated":false,"trimed":false,"spriteSourceSize":{"x":0,"y":0,"w":136,"h":95},"sourceSize":{"w":136,"h":95}},"NPC-557.png":{"frame":{"x":1628,"y":3,"w":49,"h":135},"rotated":false,"trimed":false,"spriteSourceSize":{"x":0,"y":0,"w":49,"h":135},"sourceSize":{"w":49,"h":135}},"mouse-click-asset-4.png":{"frame":{"x":1680,"y":3,"w":134,"h":134},"rotated":false,"trimed":false,"spriteSourceSize":{"x":0,"y":0,"w":134,"h":134},"sourceSize":{"w":134,"h":134}},"muzzle-flare-frame-1548.png":{"frame":{"x":671,"y":873,"w":132,"h":103},"rotated":false,"trimed":false,"spriteSourceSize":{"x":0,"y":0,"w":132,"h":103},"sourceSize":{"w":132,"h":103}},"muzzle-flare-frame-1549.png":{"frame":{"x":1817,"y":3,"w":131,"h":104},"rotated":false,"trimed":false,"spriteSourceSize":{"x":0,"y":0,"w":131,"h":104},"sourceSize":{"w":131,"h":104}},"NPC-555.png":{"frame":{"x":1951,"y":3,"w":42,"h":130},"rotated":false,"trimed":false,"spriteSourceSize":{"x":0,"y":0,"w":42,"h":130},"sourceSize":{"w":42,"h":130}},"muzzle-flare-frame-1550.png":{"frame":{"x":1817,"y":110,"w":130,"h":106},"rotated":false,"trimed":false,"spriteSourceSize":{"x":0,"y":0,"w":130,"h":106},"sourceSize":{"w":130,"h":106}},"muzzle-flare-frame-1551.png":{"frame":{"x":1682,"y":140,"w":130,"h":106},"rotated":false,"trimed":false,"spriteSourceSize":{"x":0,"y":0,"w":130,"h":106},"sourceSize":{"w":130,"h":106}},"muzzle-flare-frame-1552.png":{"frame":{"x":1815,"y":219,"w":129,"h":105},"rotated":false,"trimed":false,"spriteSourceSize":{"x":0,"y":0,"w":129,"h":105},"sourceSize":{"w":129,"h":105}},"muzzle-flare-frame-1553.png":{"frame":{"x":1682,"y":249,"w":128,"h":104},"rotated":false,"trimed":false,"spriteSourceSize":{"x":0,"y":0,"w":128,"h":104},"sourceSize":{"w":128,"h":104}},"mouse-click-asset-5.png":{"frame":{"x":1545,"y":294,"w":127,"h":127},"rotated":false,"trimed":false,"spriteSourceSize":{"x":0,"y":0,"w":127,"h":127},"sourceSize":{"w":127,"h":127}},"muzzle-flare-frame-1554.png":{"frame":{"x":1813,"y":327,"w":127,"h":102},"rotated":false,"trimed":false,"spriteSourceSize":{"x":0,"y":0,"w":127,"h":102},"sourceSize":{"w":127,"h":102}},"muzzle-flare-frame-1555.png":{"frame":{"x":1675,"y":356,"w":125,"h":101},"rotated":false,"trimed":false,"spriteSourceSize":{"x":0,"y":0,"w":125,"h":101},"sourceSize":{"w":125,"h":101}},"NPC-178.png":{"frame":{"x":1950,"y":136,"w":91,"h":124},"rotated":false,"trimed":false,"spriteSourceSize":{"x":0,"y":0,"w":91,"h":124},"sourceSize":{"w":91,"h":124}},"muzzle-flare-frame-1556.png":{"frame":{"x":1545,"y":424,"w":124,"h":100},"rotated":false,"trimed":false,"spriteSourceSize":{"x":0,"y":0,"w":124,"h":100},"sourceSize":{"w":124,"h":100}},"muzzle-flare-frame-1557.png":{"frame":{"x":1803,"y":432,"w":123,"h":100},"rotated":false,"trimed":false,"spriteSourceSize":{"x":0,"y":0,"w":123,"h":100},"sourceSize":{"w":123,"h":100}},"muzzle-flare-frame-1558.png":{"frame":{"x":1672,"y":460,"w":122,"h":99},"rotated":false,"trimed":false,"spriteSourceSize":{"x":0,"y":0,"w":122,"h":99},"sourceSize":{"w":122,"h":99}},"muzzle-flare-frame-1559.png":{"frame":{"x":1504,"y":527,"w":119,"h":97},"rotated":false,"trimed":false,"spriteSourceSize":{"x":0,"y":0,"w":119,"h":97},"sourceSize":{"w":119,"h":97}},"mouse-click-asset-3.png":{"frame":{"x":1797,"y":535,"w":119,"h":119},"rotated":false,"trimed":false,"spriteSourceSize":{"x":0,"y":0,"w":119,"h":119},"sourceSize":{"w":119,"h":119}},"muzzle-flare-frame-1560.png":{"frame":{"x":1919,"y":535,"w":118,"h":97},"rotated":false,"trimed":false,"spriteSourceSize":{"x":0,"y":0,"w":118,"h":97},"sourceSize":{"w":118,"h":97}},"NPC-306.png":{"frame":{"x":1919,"y":635,"w":109,"h":117},"rotated":false,"trimed":false,"spriteSourceSize":{"x":0,"y":0,"w":109,"h":117},"sourceSize":{"w":109,"h":117}},"muzzle-flare-frame-1561.png":{"frame":{"x":1626,"y":562,"w":116,"h":96},"rotated":false,"trimed":false,"spriteSourceSize":{"x":0,"y":0,"w":116,"h":96},"sourceSize":{"w":116,"h":96}},"muzzle-flare-frame-1562.png":{"frame":{"x":1504,"y":627,"w":114,"h":95},"rotated":false,"trimed":false,"spriteSourceSize":{"x":0,"y":0,"w":114,"h":95},"sourceSize":{"w":114,"h":95}},"muzzle-flare-frame-1563.png":{"frame":{"x":1929,"y":432,"w":112,"h":91},"rotated":false,"trimed":false,"spriteSourceSize":{"x":0,"y":0,"w":112,"h":91},"sourceSize":{"w":112,"h":91}},"NPC-169.png":{"frame":{"x":1947,"y":263,"w":85,"h":111},"rotated":false,"trimed":false,"spriteSourceSize":{"x":0,"y":0,"w":85,"h":111},"sourceSize":{"w":85,"h":111}},"mouse-click-asset-6.png":{"frame":{"x":1745,"y":657,"w":111,"h":111},"rotated":false,"trimed":false,"spriteSourceSize":{"x":0,"y":0,"w":111,"h":111},"sourceSize":{"w":111,"h":111}},"NPC-167.png":{"frame":{"x":1621,"y":661,"w":94,"h":107},"rotated":false,"trimed":false,"spriteSourceSize":{"x":0,"y":0,"w":94,"h":107},"sourceSize":{"w":94,"h":107}},"muzzle-flare-frame-1564.png":{"frame":{"x":1859,"y":755,"w":106,"h":91},"rotated":false,"trimed":false,"spriteSourceSize":{"x":0,"y":0,"w":106,"h":91},"sourceSize":{"w":106,"h":91}},"NPC-179.png":{"frame":{"x":1422,"y":849,"w":85,"h":104},"rotated":false,"trimed":false,"spriteSourceSize":{"x":0,"y":0,"w":85,"h":104},"sourceSize":{"w":85,"h":104}},"jet-ref.png":{"frame":{"x":1968,"y":755,"w":66,"h":101},"rotated":false,"trimed":false,"spriteSourceSize":{"x":0,"y":0,"w":66,"h":101},"sourceSize":{"w":66,"h":101}},"mouse-click-asset-7.png":{"frame":{"x":1510,"y":725,"w":101,"h":101},"rotated":false,"trimed":false,"spriteSourceSize":{"x":0,"y":0,"w":101,"h":101},"sourceSize":{"w":101,"h":101}},"green-square-100px.png":{"frame":{"x":1510,"y":859,"w":100,"h":100},"rotated":false,"trimed":false,"spriteSourceSize":{"x":0,"y":0,"w":100,"h":100},"sourceSize":{"w":100,"h":100}},"NPC-330.png":{"frame":{"x":932,"y":612,"w":32,"h":100},"rotated":false,"trimed":false,"spriteSourceSize":{"x":0,"y":0,"w":32,"h":100},"sourceSize":{"w":32,"h":100}},"mine-base-1.png":{"frame":{"x":1392,"y":509,"w":100,"h":8},"rotated":false,"trimed":false,"spriteSourceSize":{"x":0,"y":0,"w":100,"h":8},"sourceSize":{"w":100,"h":8}},"NPC-168.png":{"frame":{"x":1613,"y":859,"w":94,"h":98},"rotated":false,"trimed":false,"spriteSourceSize":{"x":0,"y":0,"w":94,"h":98},"sourceSize":{"w":94,"h":98}},"NPC-1.png":{"frame":{"x":1710,"y":771,"w":87,"h":97},"rotated":false,"trimed":false,"spriteSourceSize":{"x":0,"y":0,"w":87,"h":97},"sourceSize":{"w":87,"h":97}},"jet-ref-2.png":{"frame":{"x":1422,"y":709,"w":66,"h":97},"rotated":false,"trimed":false,"spriteSourceSize":{"x":0,"y":0,"w":66,"h":97},"sourceSize":{"w":66,"h":97}},"muzzle-flare-frame-1547.png":{"frame":{"x":1263,"y":941,"w":94,"h":66},"rotated":false,"trimed":false,"spriteSourceSize":{"x":0,"y":0,"w":94,"h":66},"sourceSize":{"w":94,"h":66}},"homing-mine-body-2.png":{"frame":{"x":1710,"y":871,"w":92,"h":92},"rotated":false,"trimed":false,"spriteSourceSize":{"x":0,"y":0,"w":92,"h":92},"sourceSize":{"w":92,"h":92}},"NPC-131.png":{"frame":{"x":1805,"y":859,"w":75,"h":92},"rotated":false,"trimed":false,"spriteSourceSize":{"x":0,"y":0,"w":75,"h":92},"sourceSize":{"w":75,"h":92}},"homing-mine-ref.png":{"frame":{"x":1883,"y":859,"w":92,"h":92},"rotated":false,"trimed":false,"spriteSourceSize":{"x":0,"y":0,"w":92,"h":92},"sourceSize":{"w":92,"h":92}},"mouse-click-asset-2.png":{"frame":{"x":883,"y":959,"w":91,"h":91},"rotated":false,"trimed":false,"spriteSourceSize":{"x":0,"y":0,"w":91,"h":91},"sourceSize":{"w":91,"h":91}},"muzzle-flare-frame-1566.png":{"frame":{"x":806,"y":961,"w":73,"h":90},"rotated":false,"trimed":false,"spriteSourceSize":{"x":0,"y":0,"w":73,"h":90},"sourceSize":{"w":73,"h":90}},"jet-turbine-1.png":{"frame":{"x":1613,"y":960,"w":90,"h":9},"rotated":false,"trimed":false,"spriteSourceSize":{"x":0,"y":0,"w":90,"h":9},"sourceSize":{"w":90,"h":9}},"jet-turbine-2.png":{"frame":{"x":1422,"y":829,"w":90,"h":9},"rotated":false,"trimed":false,"spriteSourceSize":{"x":0,"y":0,"w":90,"h":9},"sourceSize":{"w":90,"h":9}},"muzzle-flare-frame-1565.png":{"frame":{"x":1171,"y":980,"w":74,"h":90},"rotated":false,"trimed":false,"spriteSourceSize":{"x":0,"y":0,"w":74,"h":90},"sourceSize":{"w":74,"h":90}},"NPC-554.png":{"frame":{"x":1859,"y":657,"w":56,"h":86},"rotated":false,"trimed":false,"spriteSourceSize":{"x":0,"y":0,"w":56,"h":86},"sourceSize":{"w":56,"h":86}},"homing-mine-body-3.png":{"frame":{"x":1614,"y":771,"w":80,"h":80},"rotated":false,"trimed":false,"spriteSourceSize":{"x":0,"y":0,"w":80,"h":80},"sourceSize":{"w":80,"h":80}},"mouse-click-asset-1.png":{"frame":{"x":1075,"y":997,"w":80,"h":80},"rotated":false,"trimed":false,"spriteSourceSize":{"x":0,"y":0,"w":80,"h":80},"sourceSize":{"w":80,"h":80}},"homing-mine-jet.png":{"frame":{"x":1718,"y":661,"w":23,"h":78},"rotated":false,"trimed":false,"spriteSourceSize":{"x":0,"y":0,"w":23,"h":78},"sourceSize":{"w":23,"h":78}},"NPC-300.png":{"frame":{"x":709,"y":742,"w":75,"h":56},"rotated":false,"trimed":false,"spriteSourceSize":{"x":0,"y":0,"w":75,"h":56},"sourceSize":{"w":75,"h":56}},"NPC-129.png":{"frame":{"x":977,"y":998,"w":67,"h":73},"rotated":false,"trimed":false,"spriteSourceSize":{"x":0,"y":0,"w":67,"h":73},"sourceSize":{"w":67,"h":73}},"NPC-343.png":{"frame":{"x":1978,"y":859,"w":62,"h":57},"rotated":false,"trimed":false,"spriteSourceSize":{"x":0,"y":0,"w":62,"h":57},"sourceSize":{"w":62,"h":57}},"link-5.png":{"frame":{"x":1347,"y":709,"w":36,"h":60},"rotated":false,"trimed":false,"spriteSourceSize":{"x":0,"y":0,"w":36,"h":60},"sourceSize":{"w":36,"h":60}},"link-7.png":{"frame":{"x":1996,"y":3,"w":36,"h":60},"rotated":false,"trimed":false,"spriteSourceSize":{"x":0,"y":0,"w":36,"h":60},"sourceSize":{"w":36,"h":60}},"link-1.png":{"frame":{"x":1248,"y":980,"w":12,"h":60},"rotated":false,"trimed":false,"spriteSourceSize":{"x":0,"y":0,"w":12,"h":60},"sourceSize":{"w":12,"h":60}},"link-8.png":{"frame":{"x":1996,"y":66,"w":36,"h":59},"rotated":false,"trimed":false,"spriteSourceSize":{"x":0,"y":0,"w":36,"h":59},"sourceSize":{"w":36,"h":59}},"NPC-342.png":{"frame":{"x":1485,"y":295,"w":57,"h":38},"rotated":false,"trimed":false,"spriteSourceSize":{"x":0,"y":0,"w":57,"h":38},"sourceSize":{"w":57,"h":38}},"link-6.png":{"frame":{"x":1745,"y":562,"w":36,"h":54},"rotated":false,"trimed":false,"spriteSourceSize":{"x":0,"y":0,"w":36,"h":54},"sourceSize":{"w":36,"h":54}},"NPC-2.png":{"frame":{"x":1800,"y":771,"w":53,"h":45},"rotated":false,"trimed":false,"spriteSourceSize":{"x":0,"y":0,"w":53,"h":45},"sourceSize":{"w":53,"h":45}},"link-2.png":{"frame":{"x":1943,"y":377,"w":12,"h":52},"rotated":false,"trimed":false,"spriteSourceSize":{"x":0,"y":0,"w":12,"h":52},"sourceSize":{"w":12,"h":52}},"muzzle-flare-frame-1546.png":{"frame":{"x":1262,"y":356,"w":50,"h":30},"rotated":false,"trimed":false,"spriteSourceSize":{"x":0,"y":0,"w":50,"h":30},"sourceSize":{"w":50,"h":30}},"NPC-553.png":{"frame":{"x":78,"y":753,"w":50,"h":44},"rotated":false,"trimed":false,"spriteSourceSize":{"x":0,"y":0,"w":50,"h":44},"sourceSize":{"w":50,"h":44}},"link-4.png":{"frame":{"x":131,"y":753,"w":12,"h":49},"rotated":false,"trimed":false,"spriteSourceSize":{"x":0,"y":0,"w":12,"h":49},"sourceSize":{"w":12,"h":49}},"link-3.png":{"frame":{"x":146,"y":753,"w":12,"h":46},"rotated":false,"trimed":false,"spriteSourceSize":{"x":0,"y":0,"w":12,"h":46},"sourceSize":{"w":12,"h":46}},"metal-animation-piece-1231.png":{"frame":{"x":1510,"y":841,"w":42,"h":15},"rotated":false,"trimed":false,"spriteSourceSize":{"x":0,"y":0,"w":42,"h":15},"sourceSize":{"w":42,"h":15}},"metal-animation-piece-1227.png":{"frame":{"x":787,"y":742,"w":15,"h":42},"rotated":false,"trimed":false,"spriteSourceSize":{"x":0,"y":0,"w":15,"h":42},"sourceSize":{"w":15,"h":42}},"metal-animation-piece-1230.png":{"frame":{"x":1800,"y":819,"w":32,"h":37},"rotated":false,"trimed":false,"spriteSourceSize":{"x":0,"y":0,"w":32,"h":37},"sourceSize":{"w":32,"h":37}},"metal-animation-piece-1236.png":{"frame":{"x":1745,"y":619,"w":28,"h":33},"rotated":false,"trimed":false,"spriteSourceSize":{"x":0,"y":0,"w":28,"h":33},"sourceSize":{"w":28,"h":33}},"metal-animation-piece-1232.png":{"frame":{"x":1386,"y":709,"w":32,"h":28},"rotated":false,"trimed":false,"spriteSourceSize":{"x":0,"y":0,"w":32,"h":28},"sourceSize":{"w":32,"h":28}},"metal-animation-piece-1226.png":{"frame":{"x":1386,"y":740,"w":32,"h":28},"rotated":false,"trimed":false,"spriteSourceSize":{"x":0,"y":0,"w":32,"h":28},"sourceSize":{"w":32,"h":28}},"metal-animation-piece-1234.png":{"frame":{"x":1268,"y":164,"w":31,"h":26},"rotated":false,"trimed":false,"spriteSourceSize":{"x":0,"y":0,"w":31,"h":26},"sourceSize":{"w":31,"h":26}},"metal-animation-piece-1235.png":{"frame":{"x":1315,"y":356,"w":31,"h":30},"rotated":false,"trimed":false,"spriteSourceSize":{"x":0,"y":0,"w":31,"h":30},"sourceSize":{"w":31,"h":30}},"metal-animation-piece-1233.png":{"frame":{"x":1349,"y":356,"w":30,"h":30},"rotated":false,"trimed":false,"spriteSourceSize":{"x":0,"y":0,"w":30,"h":30},"sourceSize":{"w":30,"h":30}},"metal-animation-piece-1237.png":{"frame":{"x":1392,"y":520,"w":29,"h":29},"rotated":false,"trimed":false,"spriteSourceSize":{"x":0,"y":0,"w":29,"h":29},"sourceSize":{"w":29,"h":29}},"metal-animation-piece-1228.png":{"frame":{"x":932,"y":715,"w":26,"h":22},"rotated":false,"trimed":false,"spriteSourceSize":{"x":0,"y":0,"w":26,"h":22},"sourceSize":{"w":26,"h":22}},"metal-animation-piece-1229.png":{"frame":{"x":1718,"y":742,"w":24,"h":24},"rotated":false,"trimed":false,"spriteSourceSize":{"x":0,"y":0,"w":24,"h":24},"sourceSize":{"w":24,"h":24}},"harpoon-gun-light-back.png":{"frame":{"x":553,"y":407,"w":20,"h":20},"rotated":false,"trimed":false,"spriteSourceSize":{"x":0,"y":0,"w":20,"h":20},"sourceSize":{"w":20,"h":20}},"mine-light-off.png":{"frame":{"x":1386,"y":771,"w":16,"h":8},"rotated":false,"trimed":false,"spriteSourceSize":{"x":0,"y":0,"w":16,"h":8},"sourceSize":{"w":16,"h":8}},"homing-mine-light-4.png":{"frame":{"x":787,"y":787,"w":16,"h":16},"rotated":false,"trimed":false,"spriteSourceSize":{"x":0,"y":0,"w":16,"h":16},"sourceSize":{"w":16,"h":16}},"mine-light-red.png":{"frame":{"x":1491,"y":725,"w":16,"h":8},"rotated":false,"trimed":false,"spriteSourceSize":{"x":0,"y":0,"w":16,"h":8},"sourceSize":{"w":16,"h":8}},"homing-mine-light-3.png":{"frame":{"x":1491,"y":736,"w":16,"h":16},"rotated":false,"trimed":false,"spriteSourceSize":{"x":0,"y":0,"w":16,"h":16},"sourceSize":{"w":16,"h":16}},"homing-mine-light-1.png":{"frame":{"x":1491,"y":755,"w":16,"h":16},"rotated":false,"trimed":false,"spriteSourceSize":{"x":0,"y":0,"w":16,"h":16},"sourceSize":{"w":16,"h":16}},"homing-mine-light-2.png":{"frame":{"x":1491,"y":774,"w":16,"h":16},"rotated":false,"trimed":false,"spriteSourceSize":{"x":0,"y":0,"w":16,"h":16},"sourceSize":{"w":16,"h":16}},"harpoon-gun-light-3.png":{"frame":{"x":961,"y":715,"w":12,"h":12},"rotated":false,"trimed":false,"spriteSourceSize":{"x":0,"y":0,"w":12,"h":12},"sourceSize":{"w":12,"h":12}},"harpoon-gun-light-1.png":{"frame":{"x":1495,"y":509,"w":12,"h":12},"rotated":false,"trimed":false,"spriteSourceSize":{"x":0,"y":0,"w":12,"h":12},"sourceSize":{"w":12,"h":12}},"harpoon-gun-light-4.png":{"frame":{"x":1510,"y":509,"w":12,"h":12},"rotated":false,"trimed":false,"spriteSourceSize":{"x":0,"y":0,"w":12,"h":12},"sourceSize":{"w":12,"h":12}},"harpoon-gun-light-2.png":{"frame":{"x":1525,"y":509,"w":12,"h":12},"rotated":false,"trimed":false,"spriteSourceSize":{"x":0,"y":0,"w":12,"h":12},"sourceSize":{"w":12,"h":12}}},"meta":{"image":"d.png","format":"RGBA8888","size":{"w":2048,"h":2048},"scale":1}}
